{
  "info": {
    "name": "Vacinas App API",
    "description": "Colecao Postman para a API de consulta de pacientes e vacinas.",
    "schema": "https://schema.getpostman.com/json/collection/v2.1.0/collection.json"
  },
  "variable": [
    {
      "key": "baseUrl",
      "value": "http://localhost:8083"
    },
    {
      "key": "query",
      "value": "123.456.789-01"
    },
    {
      "key": "pacienteId",
      "value": "1"
    },
    {
      "key": "idAplicacao",
      "value": "1"
    }
  ],
  "item": [
    {
      "name": "Health - Swagger Docs",
      "request": {
        "method": "GET",
        "header": [],
        "url": {
          "raw": "{{baseUrl}}/v3/api-docs",
          "host": [
            "{{baseUrl}}"
          ],
          "path": [
            "v3",
            "api-docs"
          ]
        }
      }
    },
    {
      "name": "Pacientes",
      "item": [
        {
          "name": "Buscar por Query (CPF ou Nome)",
          "request": {
            "method": "GET",
            "header": [],
            "url": {
              "raw": "{{baseUrl}}/api/pacientes/search?query={{query}}",
              "host": [
                "{{baseUrl}}"
              ],
              "path": [
                "api",
                "pacientes",
                "search"
              ],
              "query": [
                {
                  "key": "query",
                  "value": "{{query}}"
                }
              ]
            }
          }
        },
        {
          "name": "Buscar Paciente por Id",
          "request": {
            "method": "GET",
            "header": [],
            "url": {
              "raw": "{{baseUrl}}/api/pacientes/{{pacienteId}}",
              "host": [
                "{{baseUrl}}"
              ],
              "path": [
                "api",
                "pacientes",
                "{{pacienteId}}"
              ]
            }
          }
        },
        {
          "name": "Listar Vacinas por Paciente",
          "request": {
            "method": "GET",
            "header": [],
            "url": {
              "raw": "{{baseUrl}}/api/pacientes/{{pacienteId}}/vacinas",
              "host": [
                "{{baseUrl}}"
              ],
              "path": [
                "api",
                "pacientes",
                "{{pacienteId}}",
                "vacinas"
              ]
            }
          }
        },
        {
          "name": "Buscar Histórico de Prontuário por Paciente",
          "request": {
            "method": "GET",
            "header": [],
            "url": {
              "raw": "{{baseUrl}}/api/prontuario/{{pacienteId}}",
              "host": [
                "{{baseUrl}}"
              ],
              "path": [
                "api",
                "prontuario",
                "{{pacienteId}}"
              ]
            }
          }
        }
      ]
    },
    {
      "name": "Vacinas",
      "item": [
        {
          "name": "Detalhar Aplicacao por Id",
          "request": {
            "method": "GET",
            "header": [],
            "url": {
              "raw": "{{baseUrl}}/api/vacinas/aplicacoes/{{idAplicacao}}",
              "host": [
                "{{baseUrl}}"
              ],
              "path": [
                "api",
                "vacinas",
                "aplicacoes",
                "{{idAplicacao}}"
              ]
            }
          }
        }
      ]
    },
    {
      "name": "Atendimentos",
      "item": [
        {
          "name": "Listar Exames por Atendimento",
          "request": {
            "method": "GET",
            "header": [],
            "url": {
              "raw": "{{baseUrl}}/api/atendimentos/1/exames",
              "host": [
                "{{baseUrl}}"
              ],
              "path": [
                "api",
                "atendimentos",
                "1",
                "exames"
              ]
            }
          }
        }
      ]
    },
    {
      "name": "RAAS PSI",
      "item": [
        {
          "name": "Listar Arquivos Gerados",
          "request": {
            "method": "GET",
            "header": [],
            "url": {
              "raw": "{{baseUrl}}/api/raas-psi/arquivos?competencia=&unidade_id=&unidade=&situacao=&page=&size=",
              "host": [
                "{{baseUrl}}"
              ],
              "path": [
                "api",
                "raas-psi",
                "arquivos"
              ],
              "query": [
                { "key": "competencia", "value": "", "description": "Competência para filtro (opcional)" },
                { "key": "unidade_id", "value": "", "description": "ID da unidade para filtro (opcional)" },
                { "key": "unidade", "value": "", "description": "Nome da unidade para filtro (opcional)" },
                { "key": "situacao", "value": "", "description": "Situação para filtro (opcional)" },
                { "key": "page", "value": "", "description": "Página para paginação (opcional)" },
                { "key": "size", "value": "", "description": "Tamanho da página (opcional)" }
              ]
            }
          },
          "response": []
        }
      ]
    }
  ]
}
